<annotation>
	<folder>resized</folder>
	<filename>30.jpg</filename>
	<path>E:\Selfies\resized\30.jpg</path>
	<source>
		<database>Unknown</database>
	</source>
	<size>
		<width>600</width>
		<height>600</height>
		<depth>3</depth>
	</size>
	<segmented>0</segmented>
	<object>
		<name>nike</name>
		<pose>Unspecified</pose>
		<truncated>0</truncated>
		<difficult>0</difficult>
		<bndbox>
			<xmin>239</xmin>
			<ymin>455</ymin>
			<xmax>296</xmax>
			<ymax>481</ymax>
		</bndbox>
	</object>
</annotation>
